time_range/__init__.py
time_range/time_range.py
time_range-0.1.0.dist-info/METADATA
time_range-0.1.0.dist-info/RECORD
time_range-0.1.0.dist-info/WHEEL
time_range-0.1.0.dist-info/top_level.txt
