Metadata-Version: 2.1
Name: time-range
Version: 0.1.0
Summary: Methods for handling time range overlaps for scheduling, taxes, and physics applications.
Home-page: https://github.com/tunnell/time_range
Author: Christopher Tunnell
Author-email: christopher.douglas.tunnell@gmail.com
License: GNU General Public License v3
Keywords: time_range
Platform: UNKNOWN
Classifier: Development Status :: 2 - Pre-Alpha
Classifier: Intended Audience :: Developers
Classifier: License :: OSI Approved :: GNU General Public License v3 (GPLv3)
Classifier: Natural Language :: English
Classifier: Programming Language :: Python :: 2
Classifier: Programming Language :: Python :: 2.7
Classifier: Programming Language :: Python :: 3
Classifier: Programming Language :: Python :: 3.4
Classifier: Programming Language :: Python :: 3.5
Classifier: Programming Language :: Python :: 3.6
Requires-Dist: numpy (==1.14.0)
Requires-Dist: pandas (==0.22.0)
Requires-Dist: workalendar (==2.3.1)
